{
  "luke": {
    "todo_list": {
      "creator": "luke",
      "dateCreated": "2025-06-04T17:10:12.294Z",
      "lastModified": "2025-06-04T17:10:12.294Z"
    },
    "yellow": {
      "creator": "luke",
      "dateCreated": "2025-06-02T22:40:57.337Z",
      "lastModified": "2025-06-15T14:21:05.688Z"
    },
    "renameAccessTest": {
      "creator": "walt1",
      "dateCreated": "2025-06-15T14:23:13.921Z",
      "lastModified": "2025-06-15T14:30:17.295Z"
    },
    "new": {
      "creator": "walt1",
      "dateCreated": "2025-06-15T14:54:18.960Z",
      "lastModified": "2025-06-15T14:58:11.150Z"
    }
  },
  "walt1": {
    "Bob": {
      "creator": "walt1",
      "dateCreated": "2025-06-03T17:48:50.340Z",
      "lastModified": "2025-06-03T17:48:50.340Z"
    },
    "document": {
      "creator": "walt1",
      "dateCreated": "2025-06-03T17:51:25.278Z",
      "lastModified": "2025-06-03T17:51:25.278Z"
    },
    "todo_list": {
      "creator": "luke",
      "dateCreated": "2025-06-04T17:10:12.294Z",
      "lastModified": "2025-06-13T17:25:50.200Z"
    },
    "renameAccessTest": {
      "creator": "walt1",
      "dateCreated": "2025-06-15T14:23:13.921Z",
      "lastModified": "2025-06-15T14:23:13.921Z"
    },
    "new": {
      "creator": "walt1",
      "dateCreated": "2025-06-15T14:54:18.960Z",
      "lastModified": "2025-06-15T14:58:11.150Z"
    }
  },
  "Walter": {
    "2": {
      "creator": "Walter",
      "dateCreated": "2025-06-04T16:25:55.544Z",
      "lastModified": "2025-06-04T16:25:55.544Z"
    },
    "WalterFileCreate": {
      "creator": "Walter",
      "dateCreated": "2025-06-04T16:24:27.976Z",
      "lastModified": "2025-06-04T16:24:27.977Z"
    }
  }
}